datainventory/__init__.py
datainventory/_internal_store.py
datainventory/common.py
datainventory/inventory.py
datainventory/media_store.py
datainventory/model_store.py
datainventory/table_store.py
datainventory/bin/__init__.py
datainventory/bin/app.py
datainventory-0.0.5.dist-info/LICENSE
datainventory-0.0.5.dist-info/METADATA
datainventory-0.0.5.dist-info/WHEEL
datainventory-0.0.5.dist-info/entry_points.txt
datainventory-0.0.5.dist-info/top_level.txt
datainventory-0.0.5.dist-info/RECORD
