Metadata-Version: 2.1
Name: datainventory
Version: 0.0.5
Summary: Data Inventory
Author: IoT Spectator
License: MIT License
Project-URL: repository, https://github.com/iot-spectator/datainventory
Keywords: image and video database
Classifier: License :: OSI Approved :: MIT License
Classifier: Programming Language :: Python
Requires-Python: >=3.9
License-File: LICENSE
Requires-Dist: click
Requires-Dist: pandas
Requires-Dist: SQLAlchemy
